aiochemy/__init__.py
aiochemy/activerecord.py
aiochemy/base.py
aiochemy/config.py
aiochemy/demo/amodels.py
aiochemy/engine.py
aiochemy/mixins.py
aiochemy/schema.py
aiochemy/select.py
aiochemy-0.2.0.dist-info/LICENSE
aiochemy-0.2.0.dist-info/METADATA
aiochemy-0.2.0.dist-info/WHEEL
aiochemy-0.2.0.dist-info/RECORD
