Metadata-Version: 2.3
Name: aiochemy
Version: 0.2.0
Summary: 
License: Apache-2.0
Author: ant31
Author-email: 2t.antoine@gmail.com
Requires-Python: >=3.11
Classifier: License :: OSI Approved :: Apache Software License
Classifier: Programming Language :: Python :: 3
Classifier: Programming Language :: Python :: 3.11
Classifier: Programming Language :: Python :: 3.12
Classifier: Programming Language :: Python :: 3.13
Requires-Dist: alembic (>=1.15.2,<2.0.0)
Requires-Dist: asyncpg
Requires-Dist: psycopg2 (>=2)
Requires-Dist: pydantic (>=2)
Requires-Dist: sqlalchemy (>=2)
